Soccerytics/__init__.py
Soccerytics/datafilter.py
Soccerytics/extract.py
Soccerytics/plot.py
Soccerytics-0.0.1.dist-info/METADATA
Soccerytics-0.0.1.dist-info/WHEEL
Soccerytics-0.0.1.dist-info/top_level.txt
Soccerytics-0.0.1.dist-info/RECORD
